wslfp/__init__.py
wslfp/amplitude.py
wslfp/mazzoni15-rdf.npy
wslfp/spk2curr.py
wslfp-0.2.3.dist-info/LICENSE
wslfp-0.2.3.dist-info/METADATA
wslfp-0.2.3.dist-info/WHEEL
wslfp-0.2.3.dist-info/RECORD
