Metadata-Version: 2.3
Name: wslfp
Version: 0.2.3
Summary: Weighted Sum Local Field Potentials - Implementation of the proxy method for point neurons from Mazzoni, Lindén et al., 2015
License: MIT
Author: Kyle Johnsen
Author-email: kyle@kjohnsen.org
Requires-Python: >=3.10,<4.0
Classifier: Development Status :: 4 - Beta
Classifier: Intended Audience :: Science/Research
Classifier: License :: OSI Approved :: MIT License
Classifier: Programming Language :: Python :: 3
Classifier: Programming Language :: Python :: 3.10
Classifier: Programming Language :: Python :: 3.11
Classifier: Programming Language :: Python :: 3.12
Classifier: Programming Language :: Python :: 3.13
Classifier: Programming Language :: Python :: 3.9
Classifier: Topic :: Scientific/Engineering :: Physics
Requires-Dist: attrs (>=23.2.0,<24.0.0)
Requires-Dist: matplotlib (>=3.4,<4.0)
Requires-Dist: numpy (>=1.16)
Requires-Dist: scipy (>=1.7)
Project-URL: Repository, https://github.com/siplab-gt/wslfp
